{
    "data": [
        {
            "id": 1,
            "name": "Sleep Head Lamp",
            "picture": "https://www.lightology.com/img/prod/650/873336.jpg",
            "desc": "Soft Yet Serious. The Dome Shade Is Inspired By Traditional Coil Pots, Where Ropes Of Clay Are Stacked Then Smoothed",
            "price" : "$50"
        },
        {
            "id": 2,
            "name": "Dome Table Lamp",
            "picture": "https://media.revistaad.es/photos/6176945a289a522423bdda2b/master/w_1280%2Cc_limit/++InCommonWith_DomeTableLamp_TanClay-Bone_460x.jpeg",
            "desc": "Soft Yet Serious. The Dome Shade Is Inspired By Traditional Coil Pots, Where Ropes Of Clay Are Stacked Then Smoothed",
            "price" : "$320"
        },
        {
            "id": 3,
            "name": "Sleep Head Lamp",
            "picture": "https://ae01.alicdn.com/kf/H2316904026fb42d4a3cf69d58203c3f5K/Iskandinav-okuma-masas-lambalar-yatak-odas-ba-ucu-masif-ah-ap-masa-lambas-otel-odas-lamba.jpg_Q90.jpg_.webp",
            "desc": "Soft Yet Serious. The Dome Shade Is Inspired By Traditional Coil Pots, Where Ropes Of Clay Are Stacked Then Smoothed",
            "price" : "50$"
        },
        {
            "id": 4,
            "name": "Sleep Head Lamp",
            "picture": "http://2.bp.blogspot.com/-LA6BHR86vXY/Uz6dhGuHjiI/AAAAAAAAZfA/rOw2VKlDzpM/s1600/Mush_Lamp_by_Garay_Studio_ayd%C4%B1nlatma-masa-lambas%C4%B1-dekor-tasar%C4%B1m-ahsap-modern-mudo-04.jpg",
            "desc": "Soft Yet Serious. The Dome Shade Is Inspired By Traditional Coil Pots, Where Ropes Of Clay Are Stacked Then Smoothed",
            "price" : "50$"
        },
        {
            "id": 5,
            "name": "Sleep Head Lamp",
            "picture": "https://i.pinimg.com/564x/57/19/32/571932d5bd01b1d5897e70a4341a0d98.jpg",
            "desc": "Soft Yet Serious. The Dome Shade Is Inspired By Traditional Coil Pots, Where Ropes Of Clay Are Stacked Then Smoothed",
            "price" : "50$"
        },
        {
            "id": 6,
            "name": "Sleep Head Lamp",
            "picture": "https://i.pinimg.com/564x/0f/4f/22/0f4f224c1c77b7d9fd9a5d6bb1bb0616.jpg",
            "desc": "Soft Yet Serious. The Dome Shade Is Inspired By Traditional Coil Pots, Where Ropes Of Clay Are Stacked Then Smoothed",
            "price" : "50$"
        }
    ]
}